hesong_utils-1.1.post2-nspkg.pth
hesong/utils/__init__.py
hesong/utils/configfile.py
hesong/utils/jsonable.py
hesong/utils/jsonrpc.py
hesong/utils/jsonutils.py
hesong/utils/loggermixin.py
hesong/utils/loggingconfig.py
hesong/utils/stringhelper.py
hesong/utils/version.py
hesong_utils-1.1.post2.dist-info/METADATA
hesong_utils-1.1.post2.dist-info/WHEEL
hesong_utils-1.1.post2.dist-info/namespace_packages.txt
hesong_utils-1.1.post2.dist-info/top_level.txt
hesong_utils-1.1.post2.dist-info/RECORD
