Metadata-Version: 2.1
Name: hesong-utils
Version: 1.1.post2
Summary: Hesong Python Utils
Home-page: http://bitbucket.org/hesong-opensource/hesong-python-utils
Author: liu xue yan
Author-email: liu_xue_yan@foxmail.com
License: BSD
Platform: UNKNOWN
Requires-Python: >=2.6
Provides-Extra: all
Requires-Dist: PyYAML ; extra == 'all'
Requires-Dist: ujson ; extra == 'all'
Provides-Extra: ujson
Requires-Dist: ujson ; extra == 'ujson'
Provides-Extra: yaml
Requires-Dist: PyYAML ; extra == 'yaml'
